{
  "title": "Idea netsetter(Huawei EG162G)",
  "url": "https://wiki.archlinux.org/title/Idea_netsetter(Huawei_EG162G)",
  "sections": [
    {
      "title": "Introduction",
      "level": 1,
      "content": "The HUAWEI EG162G is a EDGE/GPRS modem used for wireless internet access. The Linux kernel has supported this at least from version 2.6.29.4, and thus setting this up is not very hard.\n\n"
    },
    {
      "title": "Plug it in",
      "level": 2,
      "content": "Plug in the device, wait for a few seconds and then run:\n\n```\n$ ls /dev/ttyUSB*\n```\n\nyou will see something like this:\n\n```\n/dev/ttyUSB1  /dev/ttyUSB2  /dev/ttyUSB3\n```\n\nthe first one is the port of the modem.\n\n"
    },
    {
      "title": "Installation",
      "level": 2,
      "content": "Now install ppp and wvdial, which is a dialer.\n\n"
    },
    {
      "title": "Configuration",
      "level": 2,
      "content": "Edit your /etc/wvdial.conf and use this if you are using an idea netsetter, else use google to find the right config for your provider:\n\n```\n/etc/wvdial.conf\n```\n\n```\n[Dialer Defaults]\nModem=/dev/ttyUSB1\nBaud = 460800\nInit 1 = AT+CGMM\nInit 2 = AT+CMEE=1\nInit 3 = ATE0\nInit 4 = AT^HS=0,0\nInit 5 = AT+CFUN?\nInit 6 = AT+CLCK=\"SC\",2\nInit 7 = AT+CPIN?\nInit 8 = AT+CLCK=\"SC\",2\nModem Type = USB MODEM\nPhone=*99#\nUsername = idea\nPassword = idea\nDial Command=ATDT\nStupid Mode=1\nISDN=0\n```\n\nRemember that the modem might get a different port each time you plug it in so you might need to change the Modem=/dev/ttyUSB1 each time. For example if the output of:\n\n```\n$ ls /dev/ttyUSB*\n```\n\nis\n\n```\n/dev/ttyUSB0\n/dev/ttyUSB1\n/dev/ttyUSB2\n```\n\nthen you need to change the 2nd line in the wvdial config to Modem=/dev/ttyUSB0.\n\nIf the output of:\n\n```\n$ ls /dev/ttyUSB*\n```\n\nshows a /dev/ttyUSB_utps_modem, which will be a soft link to your Idea Netsetter's modem, change the 2nd line in the wvdial config to Modem=/dev/ttyUSB_utps_modem. This link will not change every time you reconnect the device.\n\n"
    },
    {
      "title": "Usage",
      "level": 2,
      "content": "Now all you need to do is run wvdial as root:\n\n```\n# wvdial\n```\n\nIf the connection is successful you will see something like this:\n\n```\n# wvdial\n```\n\n```\n--> WvDial: Internet dialer version 1.60\n--> Cannot get information for serial port.\n--> Initializing modem.\n--> Sending: ATZ\nATZ\nOK\n--> Modem initialized.\n--> Sending: ATDT*99#\n--> Waiting for carrier.\nATDT*99#\nCONNECT\n--> Carrier detected.  Starting PPP immediately.\n--> Starting pppd at Sun May 24 02:03:51 2009\n--> Pid of pppd: 6361\n--> Using interface ppp0\n--> pppd: è|[01]¸8A[08]È@Þ[08]\n--> pppd: è|[01]޸8A[08]È@Þ[08]\n--> pppd: è|[01]޸8AÞ[08]È@Þ[08]\n--> pppd: è|[01]¸8AÞ[08]È@Þ[08]\n--> pppd: è|[01]¸8AÞ[08]È@Þ[08]\n--> pppd: è|[01]¸8AÞ[08]È@Þ[08]\n--> local  IP address 112.110.117.241\n--> pppd: è|[01]¸8AÞ[08]È@Þ[08]\n--> remote IP address 10.64.64.64\n--> pppd: è|[01]¸8AÞ[08]È@Þ[08]\n--> primary   DNS address 10.11.12.13\n--> pppd: è|[01]¸8AÞ[08]È@Þ[08]\n--> secondary DNS address 10.11.12.14\n--> pppd: è|[01]¸8AÞ[08]È@Þ[08]\n```\n\nMake sure a DNS server is configured in order to be able to resolve domain names.\n\nIf you are already connected to a LAN, then change the subnet mask of the LAN to 255.0.0.0, and you should be able to use the LAN and the netsetter.\n\n"
    },
    {
      "title": "See also",
      "level": 2,
      "content": "- USB 3G Modem\n- USB mode switch\n\n"
    }
  ]
}