{
  "title": "ISCSI",
  "url": "https://wiki.archlinux.org/title/ISCSI",
  "sections": [
    {
      "title": "Introduction",
      "level": 1,
      "content": "With iSCSI you can access storage over an IP-based network.\n\nThe exported storage entity is the target and the importing entity is the initiator.\n\nSince Linux 2.6.38 LIO is the in-kernel iSCSI target. Before that it was tgt. SCST was another candidate for kernel inclusion.[1]\n\nThe current initiator is Open-iSCSI.\n\nIt is possible to boot Arch Linux via iSCSI.\n\n"
    },
    {
      "title": "See also",
      "level": 2,
      "content": "- Gentoo:iSCSI\n\n"
    }
  ]
}