{
  "title": "Ntp",
  "url": "https://wiki.archlinux.org/title/Ntp",
  "sections": [
    {
      "title": "Introduction",
      "level": 1,
      "content": "See Wikipedia:Network Time Protocol and Time synchronization.\n\n"
    },
    {
      "title": "Pages in category \"Network Time Protocol\"",
      "level": 2,
      "content": "The following 5 pages are in this category, out of 5 total.\n\n"
    },
    {
      "title": "C",
      "level": 3,
      "content": "- Chrony\n\n"
    },
    {
      "title": "N",
      "level": 3,
      "content": "- Network Time Protocol daemon\n- NTPsec\n\n"
    },
    {
      "title": "O",
      "level": 3,
      "content": "- OpenNTPD\n\n"
    },
    {
      "title": "S",
      "level": 3,
      "content": "- Systemd-timesyncd\n\n"
    }
  ]
}