{
  "title": "Lexmark",
  "url": "https://wiki.archlinux.org/title/Lexmark",
  "sections": [
    {
      "title": "Introduction",
      "level": 1,
      "content": "Note: **This article or section is being considered for removal.** This article or section is being considered for removal.\n\nThis article or section is being considered for removal.\n\nLexmark is a printer- and scanner-manufacturer. See:\n\n- CUPS/Printer-specific problems#Lexmark for issues about Lexmark printers with CUPS;\n- SANE/Scanner-specific problems#Lexmark for issues about Lexmark scanners with SANE.\n\n"
    }
  ]
}