{
  "title": "Wimlib",
  "url": "https://wiki.archlinux.org/title/Wimlib",
  "sections": [
    {
      "title": "Introduction",
      "level": 1,
      "content": "WIM (Microsoft Windows Imaging Format) is a file-based disk image format for Windows. It is often used in Windows installers.\n\n"
    },
    {
      "title": "Installation",
      "level": 2,
      "content": "On Linux, install wimlib to work on these files.\n\n"
    },
    {
      "title": "View information",
      "level": 2,
      "content": "To view information about the WIM file (including but not limited to: name, index, etc…), use:\n\n```\n$ wiminfo image_file\n```\n\n"
    },
    {
      "title": "Mount",
      "level": 2,
      "content": "WIM as an image file can be mounted with the following command\n\n"
    },
    {
      "title": "Read-only mount",
      "level": 3,
      "content": "```\n# wimmount image_file index directory\n```\n\n"
    },
    {
      "title": "Mount as read/write",
      "level": 3,
      "content": "```\n# wimmountrw image_file index directory\n```\n\n"
    },
    {
      "title": "Unmount",
      "level": 3,
      "content": "```\n# wimunmount directory --commit\n```\n\nto apply the changes in the read-write mount.\n\n"
    },
    {
      "title": "Directory structure",
      "level": 2,
      "content": "To view the directory structure of a WIM image, use:\n\n```\n# wimdir image_file index\n```\n\n"
    },
    {
      "title": "Extract the image",
      "level": 2,
      "content": "To extract the full image, do:\n\n```\n# wimapply image_file index target_directory\n```\n\nIf you only need a few files from the image, use wimextract(1).\n\n"
    },
    {
      "title": "Compression",
      "level": 2,
      "content": "The Windows ISO is larger than 4GiB, so it cannot be copied to a boot disk formatted with the FAT32 file system, you will need to compress install.wim to do this:\n\n```\n# wimlib-imagex optimize install.wim --solid\n```\n\n"
    }
  ]
}